flask_feather/__init__.py
flask_feather/extension.py
flask_feather/icons.py
flask_feather-0.1.0.dist-info/LICENSE
flask_feather-0.1.0.dist-info/METADATA
flask_feather-0.1.0.dist-info/WHEEL
flask_feather-0.1.0.dist-info/top_level.txt
flask_feather-0.1.0.dist-info/RECORD
