Metadata-Version: 2.1
Name: flask-feather
Version: 0.1.0
Summary: A simple Tag to implement Feather Icons in Flask
Home-page: https://github.com/thetomcat/flask-feather
Author: Tom Vos
Author-email: tjvos1@gmail.com
License: UNKNOWN
Platform: UNKNOWN
Classifier: Development Status :: 3 - Alpha
Classifier: Framework :: Flask
Classifier: License :: OSI Approved :: Apache Software License
Classifier: Programming Language :: Python
Classifier: Programming Language :: Python :: 3
Classifier: Programming Language :: Python :: 3.6
Classifier: Programming Language :: Python :: 3.7
Classifier: Programming Language :: Python :: 3.8
Classifier: Operating System :: OS Independent
Requires-Dist: flask (>=1.1)
Requires-Dist: Jinja2
Provides-Extra: dev
Requires-Dist: pytest (>=3.7) ; extra == 'dev'
Requires-Dist: twine (>=3.2) ; extra == 'dev'
Requires-Dist: check-manifest ; extra == 'dev'
